roshelper/node.py
roshelper/__init__.py
roshelper/partialnode.py
roshelper/multipublisher.py
roshelper-0.1.6.dist-info/top_level.txt
roshelper-0.1.6.dist-info/METADATA
roshelper-0.1.6.dist-info/RECORD
roshelper-0.1.6.dist-info/DESCRIPTION.rst
roshelper-0.1.6.dist-info/metadata.json
roshelper-0.1.6.dist-info/WHEEL
