Metadata-Version: 2.0
Name: roshelper
Version: 0.1.6
Summary: Making rospy just a bit easier
Home-page: http://wallarelvo.github.io/roshelper
Author: Alex Wallar
Author-email: wallarelvo@gmail.com
License: GNU GPL V3
Platform: UNKNOWN
